PyUnleashed/PyUnleashed.py
PyUnleashed/__init__.py
PyUnleashed/api.py
pyunleashed/__init__.py
pyunleashed/api.py
PyUnleashed-1.0.6.dist-info/LICENSE
PyUnleashed-1.0.6.dist-info/METADATA
PyUnleashed-1.0.6.dist-info/WHEEL
PyUnleashed-1.0.6.dist-info/top_level.txt
PyUnleashed-1.0.6.dist-info/RECORD
