Metadata-Version: 2.1
Name: PyUnleashed
Version: 1.0.6
Summary: A wrapper with a couple of utility functions for the Unleashed Software API
Home-page: https://www.adminify.me
Author: John Horton
Author-email: pyunleashed@outlook.com
License: LICENSE.txt
Platform: UNKNOWN
Classifier: Programming Language :: Python :: 3
Classifier: License :: OSI Approved :: MIT License
Classifier: Operating System :: OS Independent
Requires-Dist: requests
